praline/__init__.py
praline/dialog.py
praline/main.py
praline-0.0.7.dist-info/DESCRIPTION.rst
praline-0.0.7.dist-info/METADATA
praline-0.0.7.dist-info/RECORD
praline-0.0.7.dist-info/WHEEL
praline-0.0.7.dist-info/entry_points.txt
praline-0.0.7.dist-info/metadata.json
praline-0.0.7.dist-info/top_level.txt
